{
	"credit": "Made with Blockbench",
	"parent": "block/block",
	"textures": {
		"particle": "block/scaffolding_top",
		"top": "block/scaffolding_top",
		"bottom": "block/scaffolding_bottom"
	},
	"elements": [
		{
			"from": [0, 14, 0],
			"to": [16, 16, 16],
			"faces": {
				"up": {"uv": [0, 0, 16, 16], "texture": "#top", "cullface": "up"},
				"down": {"uv": [0, 16, 16, 0], "texture": "#top"}
			}
		},
		{
			"from": [0, 0, 0],
			"to": [16, 16, 16],
			"faces": {
				"north": {"uv": [0, 0, 16, 16], "texture": "#bottom"},
				"east": {"uv": [0, 0, 16, 16], "texture": "#bottom"},
				"south": {"uv": [0, 0, 16, 16], "texture": "#bottom"},
				"west": {"uv": [0, 0, 16, 16], "texture": "#bottom"}
			}
		},
		{
			"from": [0, 0, 0],
			"to": [16, 2, 16],
			"faces": {
				"up": {"uv": [0, 0, 16, 16], "texture": "#top", "cullface": "up"},
				"down": {"uv": [0, 0, 16, 16], "texture": "#top"}
			}
		}
	]
}